{
  "meta": {
    "ui name": "MIYABI UI",
    "description": "A design system rooted in Japanese aesthetics — balancing Minimal restraint (侘寂 Wabi-Sabi), Bold expression (力 Chikara), Luxury refinement (雅 Miyabi), and Playful spirit (遊 Asobi).",
    "attributes": [
      "MINIMAL",
      "BOLD",
      "LUXURY",
      "PLAYFUL"
    ],
    "implementationContract": {
      "cssLayers": [
        "reset",
        "base",
        "component",
        "utility"
      ],
      "layerOrder": "reset -> base -> component -> utility",
      "noStyleOutsideLayer": true,
      "cssNesting": true,
      "colorModel": "oklch",
      "colorModeControl": "document.documentElement.style.colorScheme",
      "preferJsColorSchemeControl": true,
      "externalResetCss": false
    }
  },
  "standards": {
    "css": {
      "layers": {
        "order": [
          "reset",
          "base",
          "component",
          "utility"
        ],
        "reset": {
          "required": true,
          "snippet": "@layer reset { *, *::before, *::after { box-sizing: border-box; margin: 0; padding: 0; } }",
          "responsibility": "Only normalization / reset"
        },
        "base": {
          "responsibility": "Theme, root variables, typography, document-level elements"
        },
        "component": {
          "responsibility": "Reusable UI components only"
        },
        "utility": {
          "responsibility": "Helpers, animations, responsive utilities, state toggles"
        }
      },
      "color": {
        "allColorsFromRootVars": true,
        "hardcodedColorInComponents": false,
        "cssFunction": "light-dark()",
        "colorSchemeProperty": true,
        "preferredModeSwitch": "JavaScript",
        "allowedFormats": [
          "oklch",
          "light-dark()",
          "color-mix()"
        ],
        "darkModeRule": {
          "adjustOnly": "L",
          "preserve": [
            "C",
            "h"
          ],
          "forbidChangingHue": true,
          "forbidChangingChroma": true,
          "description": "Dark mode must preserve hue identity and chroma consistency; only lightness may change."
        },
        "darkModeReadability": {
          "description": "Readability-first dark mode rules.",
          "avoidPureBlackBackground": true,
          "avoidPureWhiteText": true,
          "preferNearBlackSurfaces": true,
          "preferSolidNeutralBordersOverAlphaOnlyHairlines": true,
          "surfaceHierarchy": {
            "background": "#121212",
            "backgroundAlt": "#181818",
            "surface": "#1B1B1B",
            "elevated": "#1E1E1E",
            "hover": "#232323"
          },
          "textHierarchy": {
            "primary": "#EDEDED",
            "secondary": "#B3B3B3",
            "tertiary": "#8C8C8C"
          },
          "borderHierarchy": {
            "subtle": "#333333",
            "default": "#3A3A3A",
            "strong": "#5A5A5A"
          }
        },
        "backgroundBorderShadowMayUse": [
          "alpha in oklch()",
          "color-mix()",
          "background-blend-mode",
          "mix-blend-mode",
          "backdrop-filter"
        ]
      },
      "visibility": {
        "directStyleDisplayMutation": false,
        "useClassToggleOnly": true,
        "stateClasses": {
          "hidden": {
            "value": "is-hidden"
          },
          "open": {
            "value": "is-open"
          },
          "active": {
            "value": "is-active"
          },
          "disabled": {
            "value": "is-disabled"
          }
        }
      }
    },
    "javascript": {
      "selectors": {
        "helpers": {
          "qs": "const qs  = (sel, root = document) => root.querySelector(sel);",
          "qsa": "const qsa = (sel, root = document) => [...root.querySelectorAll(sel)];"
        }
      },
      "naming": {
        "domElementPrefix": "$",
        "privatePrefix": "_",
        "constantCase": "UPPER_SNAKE_CASE"
      },
      "dataAttributes": [
        "data-action",
        "data-col",
        "data-row",
        "data-row-menu",
        "data-resize-col"
      ],
      "events": {
        "preferDelegation": true,
        "directBindingAllowedOnlyFor": [
          "toolbar buttons",
          "other static controls"
        ]
      },
      "syntax": {
        "optionalChaining": {
          "required": true,
          "description": "Use ?. when traversing optional DOM/state/data references"
        },
        "nullishCoalescing": {
          "required": true,
          "description": "Use ?? / ??= for null or undefined fallback only"
        },
        "spreadSyntax": {
          "required": true,
          "description": "Use ... for immutable object/array updates"
        },
        "destructuring": {
          "required": true,
          "description": "Use destructuring for dataset, options, event payloads, and state access"
        },
        "defaultingRule": {
          "preferNullishOverOr": true,
          "description": "Use ?? instead of || when false, 0, and empty string are valid values"
        }
      },
      "patterns": {
        "domAccess": {
          "rule": "Optional chaining must be used when queried elements may not exist.",
          "example": "const value = $modalOverlay?.dataset?.state ?? 'closed';"
        },
        "datasetAccess": {
          "rule": "Prefer destructuring from dataset with nullish fallback.",
          "example": "const { action = '', row = '', col = '' } = $target?.dataset ?? {};"
        },
        "immutableUpdate": {
          "rule": "Use spread syntax for state and collection updates.",
          "example": "_state = { ..._state, selectedRow: rowId };"
        },
        "arrayClone": {
          "rule": "Avoid in-place mutation when updating UI state collections.",
          "example": "const nextRows = [...rows, newRow];"
        },
        "optionsMerge": {
          "rule": "Merge user options with defaults using destructuring + spread.",
          "example": "const config = { ...DEFAULT_OPTIONS, ...options };"
        },
        "nullishDefault": {
          "rule": "Use ?? instead of || when 0, '', or false are valid.",
          "example": "const page = params.page ?? 1;"
        },
        "nullishAssign": {
          "rule": "Use ??= for lazy initialization.",
          "example": "_modalCallback ??= (() => {});"
        }
      },
      "examples": {
        "safeDomAccess": "const label = $row?.querySelector('[data-label]')?.textContent ?? '';",
        "datasetDestructuring": "const { action = '', row = '', col = '' } = $target?.dataset ?? {};",
        "statePatch": "_state = { ..._state, ...patch };",
        "listClone": "const nextItems = [...items, newItem];",
        "nullishAssign": "_modalCallback ??= (() => {});"
      }
    },
    "security": {
      "sanitizeBeforeHtmlInsert": true,
      "sanitizer": "escapeHTML()"
    },
    "interaction": {
      "destructiveActionRequiresModalConfirm": true,
      "buttonRequiresTitleAttribute": true,
      "disabledButtonCursor": "not-allowed",
      "disabledStateRules": {
        "disabledDoesNotUseHoverStyle": true,
        "disabledDoesNotUseFocusStyle": true,
        "disabledDoesNotAnimate": true,
        "disabledUsesDedicatedTokens": true
      }
    },
    "icons": {
      "provider": "Material Symbols and Icons",
      "faviconProvider": "Material Symbols and Icons",
      "defaultSelectIcon": "keyboard_arrow_down",
      "defaultAccordionIcon": "expand_more",
      "defaultModalCloseIcon": "close"
    }
  },
  "color": {
    "_description": "All palette values are defined in OKLCH. Semantic dark mode values preserve C and h while adjusting L only. Dark surfaces are tuned for readability-first near-black UI.",
    "_format": "oklch",
    "primitive": {
      "sumi": {
        "50": {
          "value": "oklch(97.34% 0.0029 84.56)"
        },
        "100": {
          "value": "oklch(94.05% 0.0058 84.57)"
        },
        "200": {
          "value": "oklch(86.19% 0.0105 81.79)"
        },
        "300": {
          "value": "oklch(74.01% 0.0157 80.69)"
        },
        "400": {
          "value": "oklch(61.29% 0.0183 79.30)"
        },
        "500": {
          "value": "oklch(50.64% 0.0191 79.25)"
        },
        "600": {
          "value": "oklch(40.10% 0.0168 78.10)"
        },
        "700": {
          "value": "oklch(31.92% 0.0118 78.14)"
        },
        "800": {
          "value": "oklch(24.83% 0.0152 89.92)"
        },
        "900": {
          "value": "oklch(18.38% 0.0052 67.50)"
        },
        "950": {
          "value": "oklch(14.06% 0.0030 69.39)"
        }
      },
      "shu": {
        "50": {
          "value": "oklch(96.94% 0.0141 39.42)"
        },
        "100": {
          "value": "oklch(92.78% 0.0349 39.99)"
        },
        "200": {
          "value": "oklch(85.80% 0.0725 39.86)"
        },
        "300": {
          "value": "oklch(76.83% 0.1259 37.80)"
        },
        "400": {
          "value": "oklch(68.77% 0.1777 34.06)"
        },
        "500": {
          "value": "oklch(59.64% 0.1916 34.39)"
        },
        "600": {
          "value": "oklch(51.84% 0.1693 33.87)"
        },
        "700": {
          "value": "oklch(43.66% 0.1389 33.80)"
        },
        "800": {
          "value": "oklch(36.14% 0.1087 33.31)"
        },
        "900": {
          "value": "oklch(28.68% 0.0782 31.39)"
        },
        "950": {
          "value": "oklch(21.35% 0.0523 29.50)"
        }
      },
      "ai": {
        "50": {
          "value": "oklch(96.41% 0.0093 242.84)"
        },
        "100": {
          "value": "oklch(91.39% 0.0220 239.45)"
        },
        "200": {
          "value": "oklch(83.03% 0.0447 239.91)"
        },
        "300": {
          "value": "oklch(72.19% 0.0676 232.96)"
        },
        "400": {
          "value": "oklch(61.50% 0.0845 234.37)"
        },
        "500": {
          "value": "oklch(50.16% 0.0796 233.66)"
        },
        "600": {
          "value": "oklch(40.85% 0.0669 232.20)"
        },
        "700": {
          "value": "oklch(34.15% 0.0548 232.77)"
        },
        "800": {
          "value": "oklch(29.00% 0.0448 233.03)"
        },
        "900": {
          "value": "oklch(24.15% 0.0387 239.09)"
        },
        "950": {
          "value": "oklch(17.18% 0.0253 243.41)"
        }
      },
      "kin": {
        "50": {
          "value": "oklch(98.82% 0.0151 90.23)"
        },
        "100": {
          "value": "oklch(96.80% 0.0369 90.06)"
        },
        "200": {
          "value": "oklch(93.24% 0.0767 89.40)"
        },
        "300": {
          "value": "oklch(88.29% 0.1169 87.63)"
        },
        "400": {
          "value": "oklch(80.50% 0.1453 86.62)"
        },
        "500": {
          "value": "oklch(70.67% 0.1316 86.72)"
        },
        "600": {
          "value": "oklch(60.01% 0.1115 86.84)"
        },
        "700": {
          "value": "oklch(48.40% 0.0881 87.25)"
        },
        "800": {
          "value": "oklch(38.13% 0.0665 86.87)"
        },
        "900": {
          "value": "oklch(29.19% 0.0475 80.52)"
        },
        "950": {
          "value": "oklch(19.19% 0.0249 80.55)"
        }
      },
      "matcha": {
        "50": {
          "value": "oklch(96.85% 0.0090 134.87)"
        },
        "100": {
          "value": "oklch(92.48% 0.0250 132.13)"
        },
        "200": {
          "value": "oklch(84.91% 0.0497 133.03)"
        },
        "300": {
          "value": "oklch(74.43% 0.0790 135.83)"
        },
        "400": {
          "value": "oklch(63.89% 0.0986 137.67)"
        },
        "500": {
          "value": "oklch(53.57% 0.0921 137.96)"
        },
        "600": {
          "value": "oklch(44.62% 0.0751 137.87)"
        },
        "700": {
          "value": "oklch(36.63% 0.0573 138.60)"
        },
        "800": {
          "value": "oklch(30.03% 0.0424 138.42)"
        },
        "900": {
          "value": "oklch(24.12% 0.0288 140.71)"
        },
        "950": {
          "value": "oklch(17.32% 0.0170 141.06)"
        }
      },
      "fuji": {
        "50": {
          "value": "oklch(96.32% 0.0102 311.18)"
        },
        "100": {
          "value": "oklch(91.46% 0.0268 312.57)"
        },
        "200": {
          "value": "oklch(82.82% 0.0549 312.31)"
        },
        "300": {
          "value": "oklch(71.97% 0.0912 312.29)"
        },
        "400": {
          "value": "oklch(61.57% 0.1220 311.64)"
        },
        "500": {
          "value": "oklch(51.10% 0.1241 311.01)"
        },
        "600": {
          "value": "oklch(42.81% 0.1021 310.90)"
        },
        "700": {
          "value": "oklch(35.27% 0.0798 310.12)"
        },
        "800": {
          "value": "oklch(28.29% 0.0616 310.34)"
        },
        "900": {
          "value": "oklch(22.19% 0.0430 309.54)"
        },
        "950": {
          "value": "oklch(16.34% 0.0244 308.82)"
        }
      },
      "sakura": {
        "50": {
          "value": "oklch(97.82% 0.0108 10.33)"
        },
        "100": {
          "value": "oklch(94.38% 0.0288 9.72)"
        },
        "200": {
          "value": "oklch(88.74% 0.0608 9.50)"
        },
        "300": {
          "value": "oklch(81.00% 0.1097 12.02)"
        },
        "400": {
          "value": "oklch(73.81% 0.1621 14.45)"
        },
        "500": {
          "value": "oklch(63.74% 0.1731 15.36)"
        },
        "600": {
          "value": "oklch(54.97% 0.1601 15.28)"
        },
        "700": {
          "value": "oklch(44.94% 0.1284 14.65)"
        },
        "800": {
          "value": "oklch(35.52% 0.0954 13.36)"
        },
        "900": {
          "value": "oklch(27.60% 0.0685 10.12)"
        },
        "950": {
          "value": "oklch(19.05% 0.0379 9.86)"
        }
      }
    },
    "semantic": {
      "_description": "Purpose-driven color assignments. All CSS variables should be emitted from :root and use light-dark(). Dark mode is tuned to prioritize readable neutral surfaces, softer whites, and solid neutral borders.",
      "modeAware": {
        "primary": {
          "value": "light-dark(oklch(40.85% 0.0669 232.20), oklch(61.50% 0.0669 232.20))",
          "description": "Primary"
        },
        "primaryHover": {
          "value": "light-dark(oklch(34.15% 0.0669 232.20), oklch(72.19% 0.0669 232.20))",
          "description": "Primary hover"
        },
        "primaryActive": {
          "value": "light-dark(oklch(29.00% 0.0669 232.20), oklch(50.16% 0.0669 232.20))",
          "description": "Primary active"
        },
        "primaryMuted": {
          "value": "light-dark(oklch(91.39% 0.0220 239.45), oklch(30.00% 0.0220 239.45 / 0.22))",
          "description": "Primary muted"
        },
        "secondary": {
          "value": "light-dark(oklch(31.92% 0.0118 78.14), oklch(74.01% 0.0118 78.14))",
          "description": "Secondary"
        },
        "secondaryHover": {
          "value": "light-dark(oklch(24.83% 0.0118 78.14), oklch(86.19% 0.0118 78.14))",
          "description": "Secondary hover"
        },
        "secondaryActive": {
          "value": "light-dark(oklch(18.38% 0.0118 78.14), oklch(61.29% 0.0118 78.14))",
          "description": "Secondary active"
        },
        "secondaryMuted": {
          "value": "light-dark(oklch(94.05% 0.0058 84.57), oklch(32.00% 0.0058 84.57 / 0.18))",
          "description": "Secondary muted"
        },
        "featured": {
          "value": "light-dark(oklch(51.10% 0.1241 311.01), oklch(61.57% 0.1241 311.01))",
          "description": "Featured"
        },
        "featuredHover": {
          "value": "light-dark(oklch(42.81% 0.1241 311.01), oklch(71.97% 0.1241 311.01))",
          "description": "Featured hover"
        },
        "featuredActive": {
          "value": "light-dark(oklch(35.27% 0.1241 311.01), oklch(51.10% 0.1241 311.01))",
          "description": "Featured active"
        },
        "featuredMuted": {
          "value": "light-dark(oklch(91.46% 0.0268 312.57), oklch(30.00% 0.0268 312.57 / 0.22))",
          "description": "Featured muted"
        },
        "brand": {
          "value": "light-dark(oklch(59.64% 0.1916 34.39), oklch(68.77% 0.1916 34.39))",
          "description": "Brand"
        },
        "brandHover": {
          "value": "light-dark(oklch(51.84% 0.1916 34.39), oklch(76.83% 0.1916 34.39))",
          "description": "Brand hover"
        },
        "brandActive": {
          "value": "light-dark(oklch(43.66% 0.1916 34.39), oklch(59.64% 0.1916 34.39))",
          "description": "Brand active"
        },
        "brandMuted": {
          "value": "light-dark(oklch(92.78% 0.0349 39.99), oklch(32.00% 0.0349 39.99 / 0.18))",
          "description": "Brand muted"
        },
        "accent": {
          "value": "light-dark(oklch(80.50% 0.1453 86.62), oklch(80.50% 0.1453 86.62))",
          "description": "Accent"
        },
        "accentHover": {
          "value": "light-dark(oklch(70.67% 0.1316 86.72), oklch(88.29% 0.1316 86.72))",
          "description": "Accent hover"
        },
        "accentMuted": {
          "value": "light-dark(oklch(96.80% 0.0369 90.06), oklch(34.00% 0.0369 90.06 / 0.16))",
          "description": "Accent muted"
        },
        "success": {
          "value": "light-dark(oklch(53.57% 0.0921 137.96), oklch(63.89% 0.0921 137.96))",
          "description": "Success"
        },
        "successMuted": {
          "value": "light-dark(oklch(92.48% 0.0250 132.13), oklch(30.00% 0.0250 132.13 / 0.18))",
          "description": "Success muted"
        },
        "warning": {
          "value": "light-dark(oklch(70.67% 0.1316 86.72), oklch(80.50% 0.1316 86.72))",
          "description": "Warning"
        },
        "warningMuted": {
          "value": "light-dark(oklch(96.80% 0.0369 90.06), oklch(34.00% 0.0369 90.06 / 0.18))",
          "description": "Warning muted"
        },
        "destructive": {
          "value": "light-dark(oklch(44.94% 0.1284 14.65), oklch(63.74% 0.1284 14.65))",
          "description": "Destructive"
        },
        "destructiveHover": {
          "value": "light-dark(oklch(35.52% 0.1284 14.65), oklch(73.81% 0.1284 14.65))",
          "description": "Destructive hover"
        },
        "destructiveActive": {
          "value": "light-dark(oklch(27.60% 0.1284 14.65), oklch(54.97% 0.1284 14.65))",
          "description": "Destructive active"
        },
        "destructiveMuted": {
          "value": "light-dark(oklch(94.38% 0.0288 9.72), oklch(32.00% 0.0288 9.72 / 0.18))",
          "description": "Destructive muted"
        },
        "error": {
          "value": "light-dark(oklch(54.97% 0.1601 15.28), oklch(63.74% 0.1601 15.28))",
          "description": "Error"
        },
        "errorMuted": {
          "value": "light-dark(oklch(94.38% 0.0288 9.72), oklch(32.00% 0.0288 9.72 / 0.18))",
          "description": "Error muted"
        },
        "info": {
          "value": "light-dark(oklch(50.16% 0.0796 233.66), oklch(61.50% 0.0796 233.66))",
          "description": "Info"
        },
        "infoMuted": {
          "value": "light-dark(oklch(91.39% 0.0220 239.45), oklch(30.00% 0.0220 239.45 / 0.18))",
          "description": "Info muted"
        },
        "background": {
          "value": "light-dark(oklch(98.43% 0.0040 106.47), oklch(18.22% 0.0040 106.47))",
          "description": "Page background"
        },
        "backgroundAlt": {
          "value": "light-dark(oklch(96.05% 0.0067 97.35), oklch(20.90% 0.0067 97.35))",
          "description": "Alt background"
        },
        "backgroundElevated": {
          "value": "light-dark(oklch(100% 0 89.88), oklch(23.50% 0 89.88))",
          "description": "Elevated background"
        },
        "surface": {
          "value": "light-dark(oklch(100% 0 89.88), oklch(22.21% 0 89.88))",
          "description": "Surface"
        },
        "surfaceHover": {
          "value": "light-dark(oklch(97.34% 0.0029 84.56), oklch(25.60% 0.0029 84.56))",
          "description": "Surface hover"
        },
        "border": {
          "value": "light-dark(oklch(86.19% 0.0105 81.79), oklch(34.85% 0.0105 81.79))",
          "description": "Border"
        },
        "borderSubtle": {
          "value": "light-dark(oklch(94.05% 0.0058 84.57), oklch(32.11% 0.0058 84.57))",
          "description": "Border subtle"
        },
        "borderStrong": {
          "value": "light-dark(oklch(61.29% 0.0183 79.30), oklch(46.76% 0.0183 79.30))",
          "description": "Border strong"
        },
        "textPrimary": {
          "value": "light-dark(oklch(24.83% 0.0152 89.92), oklch(94.60% 0.0152 89.92))",
          "description": "Text primary"
        },
        "textSecondary": {
          "value": "light-dark(oklch(50.64% 0.0191 79.25), oklch(76.68% 0.0191 79.25))",
          "description": "Text secondary"
        },
        "textTertiary": {
          "value": "light-dark(oklch(61.29% 0.0183 79.30), oklch(65.00% 0.0183 79.30))",
          "description": "Text tertiary"
        },
        "textInverse": {
          "value": "light-dark(oklch(98.43% 0.0040 106.47), oklch(24.83% 0.0040 106.47))",
          "description": "Text inverse"
        },
        "textLink": {
          "value": "light-dark(oklch(40.85% 0.0669 232.20), oklch(61.50% 0.0669 232.20))",
          "description": "Text link"
        },
        "textLinkHover": {
          "value": "light-dark(oklch(34.15% 0.0548 232.77), oklch(72.19% 0.0548 232.77))",
          "description": "Text link hover"
        },
        "disabledText": {
          "value": "light-dark(oklch(69.00% 0.0183 79.30), oklch(65.34% 0.0183 79.30))",
          "description": "Disabled text"
        },
        "disabledIcon": {
          "value": "light-dark(oklch(69.00% 0.0183 79.30), oklch(65.34% 0.0183 79.30))",
          "description": "Disabled icon"
        },
        "disabledSurface": {
          "value": "light-dark(oklch(96.50% 0.0040 97.35), oklch(20.90% 0.0040 97.35))",
          "description": "Disabled surface"
        },
        "disabledBorder": {
          "value": "light-dark(oklch(90.00% 0.0060 84.57), oklch(32.11% 0.0060 84.57))",
          "description": "Disabled border"
        },
        "disabledSelectedSurface": {
          "value": "light-dark(oklch(88.00% 0.0220 239.45), oklch(38.00% 0.0220 239.45))",
          "description": "Disabled selected surface"
        },
        "disabledSelectedBorder": {
          "value": "light-dark(oklch(79.00% 0.0220 239.45), oklch(44.00% 0.0220 239.45))",
          "description": "Disabled selected border"
        },
        "disabledSelectedText": {
          "value": "light-dark(oklch(24.83% 0.0152 89.92), oklch(93.12% 0.0152 89.92))",
          "description": "Disabled selected text"
        },
        "overlay": {
          "value": "light-dark(oklch(18.38% 0.0052 67.50 / 0.48), oklch(18.38% 0.0052 67.50 / 0.64))",
          "description": "Overlay"
        },
        "focus": {
          "value": "light-dark(oklch(61.50% 0.0845 234.37), oklch(61.50% 0.0845 234.37))",
          "description": "Focus"
        }
      },
      "rootVariables": {
        "--color-primary": {
          "value": "{color.semantic.modeAware.primary.value}"
        },
        "--color-primary-hover": {
          "value": "{color.semantic.modeAware.primaryHover.value}"
        },
        "--color-primary-active": {
          "value": "{color.semantic.modeAware.primaryActive.value}"
        },
        "--color-primary-muted": {
          "value": "{color.semantic.modeAware.primaryMuted.value}"
        },
        "--color-secondary": {
          "value": "{color.semantic.modeAware.secondary.value}"
        },
        "--color-secondary-hover": {
          "value": "{color.semantic.modeAware.secondaryHover.value}"
        },
        "--color-secondary-active": {
          "value": "{color.semantic.modeAware.secondaryActive.value}"
        },
        "--color-secondary-muted": {
          "value": "{color.semantic.modeAware.secondaryMuted.value}"
        },
        "--color-featured": {
          "value": "{color.semantic.modeAware.featured.value}"
        },
        "--color-featured-hover": {
          "value": "{color.semantic.modeAware.featuredHover.value}"
        },
        "--color-featured-active": {
          "value": "{color.semantic.modeAware.featuredActive.value}"
        },
        "--color-featured-muted": {
          "value": "{color.semantic.modeAware.featuredMuted.value}"
        },
        "--color-brand": {
          "value": "{color.semantic.modeAware.brand.value}"
        },
        "--color-brand-hover": {
          "value": "{color.semantic.modeAware.brandHover.value}"
        },
        "--color-brand-active": {
          "value": "{color.semantic.modeAware.brandActive.value}"
        },
        "--color-brand-muted": {
          "value": "{color.semantic.modeAware.brandMuted.value}"
        },
        "--color-accent": {
          "value": "{color.semantic.modeAware.accent.value}"
        },
        "--color-accent-hover": {
          "value": "{color.semantic.modeAware.accentHover.value}"
        },
        "--color-accent-muted": {
          "value": "{color.semantic.modeAware.accentMuted.value}"
        },
        "--color-success": {
          "value": "{color.semantic.modeAware.success.value}"
        },
        "--color-success-muted": {
          "value": "{color.semantic.modeAware.successMuted.value}"
        },
        "--color-warning": {
          "value": "{color.semantic.modeAware.warning.value}"
        },
        "--color-warning-muted": {
          "value": "{color.semantic.modeAware.warningMuted.value}"
        },
        "--color-destructive": {
          "value": "{color.semantic.modeAware.destructive.value}"
        },
        "--color-destructive-hover": {
          "value": "{color.semantic.modeAware.destructiveHover.value}"
        },
        "--color-destructive-active": {
          "value": "{color.semantic.modeAware.destructiveActive.value}"
        },
        "--color-destructive-muted": {
          "value": "{color.semantic.modeAware.destructiveMuted.value}"
        },
        "--color-error": {
          "value": "{color.semantic.modeAware.error.value}"
        },
        "--color-error-muted": {
          "value": "{color.semantic.modeAware.errorMuted.value}"
        },
        "--color-info": {
          "value": "{color.semantic.modeAware.info.value}"
        },
        "--color-info-muted": {
          "value": "{color.semantic.modeAware.infoMuted.value}"
        },
        "--color-background": {
          "value": "{color.semantic.modeAware.background.value}"
        },
        "--color-background-alt": {
          "value": "{color.semantic.modeAware.backgroundAlt.value}"
        },
        "--color-background-elevated": {
          "value": "{color.semantic.modeAware.backgroundElevated.value}"
        },
        "--color-surface": {
          "value": "{color.semantic.modeAware.surface.value}"
        },
        "--color-surface-hover": {
          "value": "{color.semantic.modeAware.surfaceHover.value}"
        },
        "--color-border": {
          "value": "{color.semantic.modeAware.border.value}"
        },
        "--color-border-subtle": {
          "value": "{color.semantic.modeAware.borderSubtle.value}"
        },
        "--color-border-strong": {
          "value": "{color.semantic.modeAware.borderStrong.value}"
        },
        "--color-text-primary": {
          "value": "{color.semantic.modeAware.textPrimary.value}"
        },
        "--color-text-secondary": {
          "value": "{color.semantic.modeAware.textSecondary.value}"
        },
        "--color-text-tertiary": {
          "value": "{color.semantic.modeAware.textTertiary.value}"
        },
        "--color-text-inverse": {
          "value": "{color.semantic.modeAware.textInverse.value}"
        },
        "--color-text-link": {
          "value": "{color.semantic.modeAware.textLink.value}"
        },
        "--color-text-link-hover": {
          "value": "{color.semantic.modeAware.textLinkHover.value}"
        },
        "--color-disabled-text": {
          "value": "{color.semantic.modeAware.disabledText.value}"
        },
        "--color-disabled-icon": {
          "value": "{color.semantic.modeAware.disabledIcon.value}"
        },
        "--color-disabled-surface": {
          "value": "{color.semantic.modeAware.disabledSurface.value}"
        },
        "--color-disabled-border": {
          "value": "{color.semantic.modeAware.disabledBorder.value}"
        },
        "--color-disabled-selected-surface": {
          "value": "{color.semantic.modeAware.disabledSelectedSurface.value}"
        },
        "--color-disabled-selected-border": {
          "value": "{color.semantic.modeAware.disabledSelectedBorder.value}"
        },
        "--color-disabled-selected-text": {
          "value": "{color.semantic.modeAware.disabledSelectedText.value}"
        },
        "--color-overlay": {
          "value": "{color.semantic.modeAware.overlay.value}"
        },
        "--color-focus": {
          "value": "{color.semantic.modeAware.focus.value}"
        }
      }
    },
    "effects": {
      "surfaceGlass": {
        "value": "color-mix(in oklch, var(--color-surface) 76%, transparent)"
      },
      "surfaceGlassStrong": {
        "value": "color-mix(in oklch, var(--color-surface) 88%, transparent)"
      },
      "hairlineBorder": {
        "value": "color-mix(in oklch, var(--color-border) 78%, transparent)"
      },
      "luxuryGlow": {
        "value": "color-mix(in oklch, var(--color-accent) 24%, transparent)"
      }
    }
  },
  "typography": {
    "_description": "Editorial scale rooted in Japanese typographic tradition. Added compact SaaS-oriented UI scale for product usage.",
    "fontFamily": {
      "display": {
        "value": "'Shippori Mincho', 'Noto Serif JP', 'YuMincho', serif"
      },
      "heading": {
        "value": "'Shippori Mincho', 'Noto Serif JP', 'YuMincho', serif"
      },
      "body": {
        "value": "'Noto Sans JP', 'Hiragino Sans', 'Yu Gothic', sans-serif"
      },
      "mono": {
        "value": "'IBM Plex Mono', 'Source Code Pro', monospace"
      },
      "accent": {
        "value": "'Zen Kaku Gothic New', 'Noto Sans JP', sans-serif"
      }
    },
    "fontWeight": {
      "regular": {
        "value": 400
      },
      "medium": {
        "value": 500
      },
      "semibold": {
        "value": 600
      },
      "bold": {
        "value": 700
      }
    },
    "ui": {
      "caption": {
        "fontSize": {
          "value": "11px"
        },
        "lineHeight": {
          "value": "16px"
        },
        "fontWeight": {
          "value": "{typography.fontWeight.regular.value}"
        },
        "fontFamily": {
          "value": "{typography.fontFamily.accent.value}"
        }
      },
      "bodySm": {
        "fontSize": {
          "value": "12px"
        },
        "lineHeight": {
          "value": "16px"
        },
        "fontWeight": {
          "value": "{typography.fontWeight.regular.value}"
        },
        "fontFamily": {
          "value": "{typography.fontFamily.body.value}"
        }
      },
      "bodyMd": {
        "fontSize": {
          "value": "13px"
        },
        "lineHeight": {
          "value": "18px"
        },
        "fontWeight": {
          "value": "{typography.fontWeight.regular.value}"
        },
        "fontFamily": {
          "value": "{typography.fontFamily.body.value}"
        }
      },
      "bodyLg": {
        "fontSize": {
          "value": "14px"
        },
        "lineHeight": {
          "value": "20px"
        },
        "fontWeight": {
          "value": "{typography.fontWeight.regular.value}"
        },
        "fontFamily": {
          "value": "{typography.fontFamily.body.value}"
        }
      },
      "titleSm": {
        "fontSize": {
          "value": "13px"
        },
        "lineHeight": {
          "value": "18px"
        },
        "fontWeight": {
          "value": "{typography.fontWeight.medium.value}"
        },
        "fontFamily": {
          "value": "{typography.fontFamily.body.value}"
        }
      },
      "titleMd": {
        "fontSize": {
          "value": "14px"
        },
        "lineHeight": {
          "value": "20px"
        },
        "fontWeight": {
          "value": "{typography.fontWeight.medium.value}"
        },
        "fontFamily": {
          "value": "{typography.fontFamily.body.value}"
        }
      },
      "titleLg": {
        "fontSize": {
          "value": "18px"
        },
        "lineHeight": {
          "value": "24px"
        },
        "fontWeight": {
          "value": "{typography.fontWeight.semibold.value}"
        },
        "fontFamily": {
          "value": "{typography.fontFamily.body.value}"
        }
      },
      "headlineSm": {
        "fontSize": {
          "value": "20px"
        },
        "lineHeight": {
          "value": "28px"
        },
        "fontWeight": {
          "value": "{typography.fontWeight.semibold.value}"
        },
        "fontFamily": {
          "value": "{typography.fontFamily.heading.value}"
        }
      },
      "headlineMd": {
        "fontSize": {
          "value": "24px"
        },
        "lineHeight": {
          "value": "32px"
        },
        "fontWeight": {
          "value": "{typography.fontWeight.semibold.value}"
        },
        "fontFamily": {
          "value": "{typography.fontFamily.heading.value}"
        }
      },
      "headlineLg": {
        "fontSize": {
          "value": "28px"
        },
        "lineHeight": {
          "value": "36px"
        },
        "fontWeight": {
          "value": "{typography.fontWeight.bold.value}"
        },
        "fontFamily": {
          "value": "{typography.fontFamily.display.value}"
        }
      },
      "display": {
        "fontSize": {
          "value": "36px"
        },
        "lineHeight": {
          "value": "46px"
        },
        "fontWeight": {
          "value": "{typography.fontWeight.bold.value}"
        },
        "fontFamily": {
          "value": "{typography.fontFamily.display.value}"
        }
      }
    },
    "scale": {
      "display-xl": {
        "fontSize": {
          "value": "4.5rem"
        },
        "lineHeight": {
          "value": "1.1"
        },
        "letterSpacing": {
          "value": "0.04em"
        },
        "fontWeight": {
          "value": "{typography.fontWeight.bold.value}"
        },
        "fontFamily": {
          "value": "{typography.fontFamily.display.value}"
        }
      },
      "display-lg": {
        "fontSize": {
          "value": "3.5rem"
        },
        "lineHeight": {
          "value": "1.15"
        },
        "letterSpacing": {
          "value": "0.03em"
        },
        "fontWeight": {
          "value": "{typography.fontWeight.semibold.value}"
        },
        "fontFamily": {
          "value": "{typography.fontFamily.display.value}"
        }
      },
      "display-md": {
        "fontSize": {
          "value": "2.5rem"
        },
        "lineHeight": {
          "value": "1.2"
        },
        "letterSpacing": {
          "value": "0.02em"
        },
        "fontWeight": {
          "value": "{typography.fontWeight.semibold.value}"
        },
        "fontFamily": {
          "value": "{typography.fontFamily.display.value}"
        }
      },
      "heading-lg": {
        "fontSize": {
          "value": "2rem"
        },
        "lineHeight": {
          "value": "1.3"
        },
        "letterSpacing": {
          "value": "0.01em"
        },
        "fontWeight": {
          "value": "{typography.fontWeight.semibold.value}"
        },
        "fontFamily": {
          "value": "{typography.fontFamily.heading.value}"
        }
      },
      "heading-md": {
        "fontSize": {
          "value": "1.5rem"
        },
        "lineHeight": {
          "value": "1.4"
        },
        "letterSpacing": {
          "value": "0.01em"
        },
        "fontWeight": {
          "value": "{typography.fontWeight.medium.value}"
        },
        "fontFamily": {
          "value": "{typography.fontFamily.heading.value}"
        }
      },
      "heading-sm": {
        "fontSize": {
          "value": "1.25rem"
        },
        "lineHeight": {
          "value": "1.4"
        },
        "letterSpacing": {
          "value": "0.005em"
        },
        "fontWeight": {
          "value": "{typography.fontWeight.medium.value}"
        },
        "fontFamily": {
          "value": "{typography.fontFamily.heading.value}"
        }
      },
      "body-lg": {
        "fontSize": {
          "value": "1.125rem"
        },
        "lineHeight": {
          "value": "1.75"
        },
        "letterSpacing": {
          "value": "0.01em"
        },
        "fontWeight": {
          "value": "{typography.fontWeight.regular.value}"
        },
        "fontFamily": {
          "value": "{typography.fontFamily.body.value}"
        }
      },
      "body-md": {
        "fontSize": {
          "value": "1rem"
        },
        "lineHeight": {
          "value": "1.75"
        },
        "letterSpacing": {
          "value": "0.01em"
        },
        "fontWeight": {
          "value": "{typography.fontWeight.regular.value}"
        },
        "fontFamily": {
          "value": "{typography.fontFamily.body.value}"
        }
      },
      "body-sm": {
        "fontSize": {
          "value": "0.875rem"
        },
        "lineHeight": {
          "value": "1.6"
        },
        "letterSpacing": {
          "value": "0.01em"
        },
        "fontWeight": {
          "value": "{typography.fontWeight.regular.value}"
        },
        "fontFamily": {
          "value": "{typography.fontFamily.body.value}"
        }
      }
    }
  },
  "spacing": {
    "_description": "8px base grid with Japanese-inspired naming (間 Ma — the beauty of space)",
    "0": {
      "value": "0px"
    },
    "1": {
      "value": "4px"
    },
    "2": {
      "value": "8px"
    },
    "3": {
      "value": "12px"
    },
    "4": {
      "value": "16px"
    },
    "5": {
      "value": "20px"
    },
    "6": {
      "value": "24px"
    },
    "8": {
      "value": "32px"
    },
    "10": {
      "value": "40px"
    },
    "12": {
      "value": "48px"
    },
    "16": {
      "value": "64px"
    },
    "20": {
      "value": "80px"
    },
    "24": {
      "value": "96px"
    },
    "32": {
      "value": "128px"
    },
    "40": {
      "value": "160px"
    },
    "48": {
      "value": "192px"
    }
  },
  "borderRadius": {
    "none": {
      "value": "0px"
    },
    "sm": {
      "value": "4px"
    },
    "md": {
      "value": "8px"
    },
    "lg": {
      "value": "12px"
    },
    "xl": {
      "value": "16px"
    },
    "2xl": {
      "value": "24px"
    },
    "full": {
      "value": "9999px"
    }
  },
  "shadow": {
    "modeAware": {
      "sm": {
        "value": "0 1px 2px color-mix(in oklch, var(--color-text-primary) 8%, transparent), 0 1px 4px color-mix(in oklch, var(--color-text-primary) 6%, transparent)"
      },
      "md": {
        "value": "0 2px 4px color-mix(in oklch, var(--color-text-primary) 8%, transparent), 0 4px 12px color-mix(in oklch, var(--color-text-primary) 10%, transparent)"
      },
      "lg": {
        "value": "0 4px 8px color-mix(in oklch, var(--color-text-primary) 8%, transparent), 0 8px 24px color-mix(in oklch, var(--color-text-primary) 12%, transparent)"
      },
      "xl": {
        "value": "0 8px 16px color-mix(in oklch, var(--color-text-primary) 10%, transparent), 0 16px 48px color-mix(in oklch, var(--color-text-primary) 14%, transparent)"
      },
      "inner": {
        "value": "inset 0 1px 3px color-mix(in oklch, var(--color-text-primary) 10%, transparent)"
      },
      "gold": {
        "value": "0 4px 16px color-mix(in oklch, var(--color-accent) 18%, transparent), 0 1px 4px color-mix(in oklch, var(--color-accent) 12%, transparent)"
      }
    }
  },
  "animation": {
    "_description": "Motion inspired by 能 Noh — deliberate, graceful, purposeful",
    "duration": {
      "instant": {
        "value": "100ms"
      },
      "fast": {
        "value": "200ms"
      },
      "normal": {
        "value": "300ms"
      },
      "slow": {
        "value": "500ms"
      },
      "graceful": {
        "value": "800ms"
      },
      "dramatic": {
        "value": "1200ms"
      }
    },
    "easing": {
      "default": {
        "value": "cubic-bezier(0.2, 0, 0.0, 1.0)"
      },
      "enter": {
        "value": "cubic-bezier(0.0, 0.0, 0.2, 1.0)"
      },
      "exit": {
        "value": "cubic-bezier(0.4, 0.0, 1.0, 1.0)"
      },
      "spring": {
        "value": "cubic-bezier(0.34, 1.56, 0.64, 1)"
      },
      "brush": {
        "value": "cubic-bezier(0.22, 0.61, 0.36, 1)"
      }
    },
    "keyframes": {
      "fadeIn": {
        "value": "opacity: 0 -> 1"
      },
      "slideUp": {
        "value": "translateY(16px), opacity:0 -> 1"
      },
      "slideDown": {
        "value": "translateY(-16px), opacity:0 -> 1"
      },
      "slideRight": {
        "value": "translateX(-24px), opacity:0 -> 1"
      },
      "scaleIn": {
        "value": "scale(0.95), opacity:0 -> 1"
      },
      "brushReveal": {
        "value": "clip-path: inset(0 100% 0 0) -> inset(0 0 0 0)"
      },
      "inkDrop": {
        "value": "scale(0), opacity:0 -> scale(1), opacity:1 via radial expansion"
      },
      "floatUp": {
        "value": "translateY(0) -> translateY(-6px) -> translateY(0), infinite"
      }
    }
  },
  "breakpoints": {
    "sm": {
      "value": "480px"
    },
    "md": {
      "value": "768px"
    },
    "lg": {
      "value": "1024px"
    },
    "xl": {
      "value": "1280px"
    },
    "2xl": {
      "value": "1536px"
    }
  },
  "layout": {
    "container": {
      "sm": {
        "value": "640px"
      },
      "md": {
        "value": "768px"
      },
      "lg": {
        "value": "1024px"
      },
      "xl": {
        "value": "1200px"
      },
      "2xl": {
        "value": "1400px"
      }
    },
    "grid": {
      "columns": {
        "value": 12
      },
      "gutter": {
        "value": "{spacing.6}"
      },
      "margin": {
        "value": "{spacing.6}"
      }
    }
  },
  "components": {
    "_description": "Component specifications with compact SaaS-oriented UI density and accessibility-aware disabled states.",
    "formField": {
      "surface": "{color.semantic.modeAware.surface.value}",
      "surfaceAlt": "{color.semantic.modeAware.backgroundAlt.value}",
      "surfaceHover": "{color.semantic.modeAware.surfaceHover.value}",
      "text": "{color.semantic.modeAware.textPrimary.value}",
      "placeholder": "{color.semantic.modeAware.textTertiary.value}",
      "border": "{color.semantic.modeAware.border.value}",
      "borderStrong": "{color.semantic.modeAware.borderStrong.value}",
      "focusRing": "{color.semantic.modeAware.primary.value}",
      "focusHalo": "{color.semantic.modeAware.primaryMuted.value}",
      "disabledText": "{color.semantic.modeAware.disabledText.value}",
      "disabledSurface": "{color.semantic.modeAware.disabledSurface.value}",
      "disabledBorder": "{color.semantic.modeAware.disabledBorder.value}",
      "disabledSelectedSurface": "{color.semantic.modeAware.disabledSelectedSurface.value}",
      "disabledSelectedBorder": "{color.semantic.modeAware.disabledSelectedBorder.value}",
      "radius": "{borderRadius.lg}",
      "backdropFilter": "blur(12px) saturate(160%)",
      "blendMode": "normal",
      "fieldShadow": "{shadow.modeAware.sm.value}",
      "fieldInset": "inset 0 1px 0 color-mix(in oklch, var(--color-background-elevated) 72%, transparent)"
    },
    "button": {
      "variants": [
        "primary",
        "secondary",
        "featured",
        "outline",
        "ghost",
        "destructive",
        "danger",
        "luxury"
      ],
      "requiresTitleAttribute": true,
      "sizes": {
        "sm": {
          "height": "30px",
          "paddingX": "{spacing.3}",
          "fontSize": "{typography.ui.bodySm.fontSize.value}",
          "borderRadius": "{borderRadius.sm}"
        },
        "md": {
          "height": "36px",
          "paddingX": "{spacing.4}",
          "fontSize": "{typography.ui.bodyMd.fontSize.value}",
          "borderRadius": "{borderRadius.md}"
        },
        "lg": {
          "height": "44px",
          "paddingX": "{spacing.5}",
          "fontSize": "{typography.ui.bodyLg.fontSize.value}",
          "borderRadius": "{borderRadius.md}"
        },
        "xl": {
          "height": "52px",
          "paddingX": "{spacing.8}",
          "fontSize": "{typography.ui.bodyLg.fontSize.value}",
          "borderRadius": "{borderRadius.lg}"
        }
      },
      "states": {
        "default": {
          "cursor": "pointer"
        },
        "hover": {
          "transform": "translateY(-1px)",
          "transition": "{animation.duration.fast.value} {animation.easing.default.value}"
        },
        "active": {
          "transform": "translateY(0px) scale(0.98)"
        },
        "focus": {
          "outline": "2px solid var(--color-focus)",
          "outlineOffset": "2px"
        },
        "disabled": {
          "opacity": "1",
          "background": "var(--color-disabled-surface)",
          "color": "var(--color-disabled-text)",
          "border": "1px solid var(--color-disabled-border)",
          "boxShadow": "none",
          "cursor": "not-allowed",
          "pointerEvents": "none",
          "transform": "none"
        },
        "loading": {
          "opacity": "0.7",
          "cursor": "wait"
        }
      },
      "primary": {
        "background": "var(--color-primary)",
        "color": "var(--color-text-inverse)",
        "hover": {
          "background": "var(--color-primary-hover)"
        },
        "active": {
          "background": "var(--color-primary-active)"
        }
      },
      "secondary": {
        "background": "var(--color-secondary)",
        "color": "var(--color-text-inverse)",
        "hover": {
          "background": "var(--color-secondary-hover)"
        },
        "active": {
          "background": "var(--color-secondary-active)"
        }
      },
      "featured": {
        "background": "var(--color-featured)",
        "color": "var(--color-text-inverse)",
        "hover": {
          "background": "var(--color-featured-hover)"
        },
        "active": {
          "background": "var(--color-featured-active)"
        }
      },
      "outline": {
        "background": "color-mix(in oklch, var(--color-surface) 80%, transparent)",
        "color": "var(--color-text-primary)",
        "border": "1px solid var(--color-border)"
      },
      "ghost": {
        "background": "transparent",
        "color": "var(--color-text-primary)",
        "hover": {
          "background": "color-mix(in oklch, var(--color-surface-hover) 72%, transparent)"
        }
      },
      "destructive": {
        "background": "color-mix(in oklch, var(--color-surface) 88%, transparent)",
        "color": "var(--color-destructive)",
        "border": "1px solid var(--color-destructive)",
        "hover": {
          "background": "var(--color-destructive-muted)",
          "color": "var(--color-destructive-hover)",
          "border": "1px solid var(--color-destructive-hover)"
        },
        "active": {
          "background": "color-mix(in oklch, var(--color-destructive-muted) 88%, var(--color-surface))",
          "color": "var(--color-destructive-active)",
          "border": "1px solid var(--color-destructive-active)"
        }
      },
      "danger": {
        "background": "color-mix(in oklch, var(--color-surface) 88%, transparent)",
        "color": "var(--color-destructive)",
        "border": "1px solid var(--color-destructive)",
        "hover": {
          "background": "var(--color-destructive-muted)",
          "color": "var(--color-destructive-hover)",
          "border": "1px solid var(--color-destructive-hover)"
        },
        "active": {
          "background": "color-mix(in oklch, var(--color-destructive-muted) 88%, var(--color-surface))",
          "color": "var(--color-destructive-active)",
          "border": "1px solid var(--color-destructive-active)"
        }
      },
      "luxury": {
        "background": "linear-gradient(135deg, {color.primitive.kin.400.value}, {color.primitive.kin.600.value})",
        "color": "var(--color-text-inverse)",
        "border": "1px solid {color.primitive.kin.300.value}",
        "boxShadow": "{shadow.modeAware.gold.value}"
      }
    },
    "input": {
      "variants": [
        "default",
        "filled",
        "flushed",
        "brand"
      ],
      "sizes": {
        "sm": {
          "height": "30px",
          "paddingX": "{spacing.3}",
          "fontSize": "{typography.ui.bodySm.fontSize.value}"
        },
        "md": {
          "height": "36px",
          "paddingX": "{spacing.4}",
          "fontSize": "{typography.ui.bodyMd.fontSize.value}"
        },
        "lg": {
          "height": "44px",
          "paddingX": "{spacing.5}",
          "fontSize": "{typography.ui.bodyLg.fontSize.value}"
        }
      },
      "states": {
        "default": {
          "border": "1px solid var(--color-border)",
          "borderRadius": "{borderRadius.md}"
        },
        "hover": {
          "borderColor": "var(--color-border-strong)"
        },
        "focus": {
          "borderColor": "var(--color-primary)",
          "boxShadow": "0 0 0 3px var(--color-primary-muted)"
        },
        "error": {
          "borderColor": "var(--color-error)",
          "boxShadow": "0 0 0 3px var(--color-error-muted)"
        },
        "disabled": {
          "opacity": "1",
          "background": "var(--color-disabled-surface)",
          "color": "var(--color-disabled-text)",
          "borderColor": "var(--color-disabled-border)",
          "boxShadow": "none",
          "cursor": "not-allowed"
        },
        "readonly": {
          "background": "color-mix(in oklch, var(--color-background-alt) 72%, var(--color-surface))"
        }
      },
      "brand": {
        "background": "color-mix(in oklch, var(--color-surface) 88%, transparent)",
        "border": "1px solid var(--color-border)",
        "borderRadius": "{borderRadius.lg}",
        "boxShadow": "{shadow.modeAware.sm.value}, inset 0 1px 0 color-mix(in oklch, var(--color-background-elevated) 72%, transparent)",
        "backdropFilter": "blur(12px) saturate(160%)",
        "hover": {
          "background": "color-mix(in oklch, var(--color-surface-hover) 92%, transparent)",
          "borderColor": "var(--color-border-strong)"
        },
        "focus": {
          "borderColor": "var(--color-primary)",
          "boxShadow": "0 0 0 3px var(--color-primary-muted), 0 8px 24px color-mix(in oklch, var(--color-primary) 14%, transparent)"
        },
        "error": {
          "borderColor": "var(--color-error)",
          "boxShadow": "0 0 0 3px var(--color-error-muted)"
        },
        "disabled": {
          "opacity": "1",
          "background": "var(--color-disabled-surface)",
          "color": "var(--color-disabled-text)",
          "borderColor": "var(--color-disabled-border)",
          "boxShadow": "none",
          "cursor": "not-allowed"
        },
        "readonly": {
          "background": "color-mix(in oklch, var(--color-background-alt) 72%, var(--color-surface))"
        }
      }
    },
    "textarea": {
      "minHeight": "112px",
      "resize": "vertical",
      "states": "same as input",
      "variants": [
        "default",
        "filled",
        "flushed",
        "brand"
      ],
      "brand": {
        "background": "color-mix(in oklch, var(--color-surface) 88%, transparent)",
        "border": "1px solid var(--color-border)",
        "borderRadius": "{borderRadius.xl}",
        "boxShadow": "{shadow.modeAware.sm.value}, inset 0 1px 0 color-mix(in oklch, var(--color-background-elevated) 72%, transparent)",
        "focus": {
          "borderColor": "var(--color-primary)",
          "boxShadow": "0 0 0 3px var(--color-primary-muted), 0 12px 28px color-mix(in oklch, var(--color-primary) 12%, transparent)"
        },
        "disabled": {
          "opacity": "1",
          "background": "var(--color-disabled-surface)",
          "color": "var(--color-disabled-text)",
          "borderColor": "var(--color-disabled-border)",
          "boxShadow": "none",
          "cursor": "not-allowed"
        },
        "readonly": {
          "background": "color-mix(in oklch, var(--color-background-alt) 72%, var(--color-surface))",
          "color": "var(--color-text-secondary)"
        }
      }
    },
    "select": {
      "indicator": "keyboard_arrow_down",
      "iconFamily": "Material Symbols and Icons",
      "iconPosition": "inline-end",
      "states": "same as input",
      "indicatorGapEnd": {
        "value": "{spacing.3}",
        "description": "Extra space to the right of chevron-down icon"
      },
      "indicatorPaddingInlineEnd": {
        "value": "calc({spacing.5} + {spacing.3})",
        "description": "Room for icon plus right-side breathing space"
      },
      "variants": [
        "default",
        "filled",
        "flushed",
        "brand"
      ],
      "brand": {
        "background": "color-mix(in oklch, var(--color-surface) 88%, transparent)",
        "border": "1px solid var(--color-border)",
        "borderRadius": "{borderRadius.lg}",
        "boxShadow": "{shadow.modeAware.sm.value}, inset 0 1px 0 color-mix(in oklch, var(--color-background-elevated) 72%, transparent)",
        "focus": {
          "borderColor": "var(--color-primary)",
          "boxShadow": "0 0 0 3px var(--color-primary-muted), 0 8px 24px color-mix(in oklch, var(--color-primary) 12%, transparent)"
        },
        "disabled": {
          "opacity": "1",
          "background": "var(--color-disabled-surface)",
          "color": "var(--color-disabled-text)",
          "borderColor": "var(--color-disabled-border)",
          "boxShadow": "none",
          "cursor": "not-allowed"
        }
      },
      "dropdown": {
        "background": "color-mix(in oklch, var(--color-surface) 92%, transparent)",
        "boxShadow": "{shadow.modeAware.lg.value}",
        "borderRadius": "{borderRadius.xl}",
        "border": "1px solid color-mix(in oklch, var(--color-border) 88%, transparent)",
        "backdropFilter": "blur(14px) saturate(170%)",
        "maxHeight": "280px"
      }
    },
    "checkbox": {
      "size": "18px",
      "borderRadius": "{borderRadius.sm}",
      "iconFamily": "Material Symbols and Icons",
      "checkedIcon": "check",
      "indeterminateIcon": "remove",
      "states": {
        "unchecked": {
          "border": "2px solid var(--color-border)"
        },
        "checked": {
          "background": "var(--color-primary)",
          "border": "2px solid var(--color-primary)"
        },
        "indeterminate": {
          "background": "var(--color-primary)",
          "border": "2px solid var(--color-primary)"
        },
        "hover": {
          "borderColor": "var(--color-primary)"
        },
        "focus": {
          "boxShadow": "0 0 0 3px var(--color-primary-muted)"
        },
        "disabledUnchecked": {
          "background": "var(--color-disabled-surface)",
          "border": "2px solid var(--color-disabled-border)",
          "iconColor": "var(--color-disabled-icon)",
          "cursor": "not-allowed"
        },
        "disabledChecked": {
          "background": "var(--color-disabled-selected-surface)",
          "border": "2px solid var(--color-disabled-selected-border)",
          "iconColor": "var(--color-disabled-selected-text)",
          "cursor": "not-allowed"
        },
        "disabledIndeterminate": {
          "background": "var(--color-disabled-selected-surface)",
          "border": "2px solid var(--color-disabled-selected-border)",
          "iconColor": "var(--color-disabled-selected-text)",
          "cursor": "not-allowed"
        }
      },
      "brand": {
        "unchecked": {
          "background": "color-mix(in oklch, var(--color-surface) 84%, transparent)",
          "border": "2px solid var(--color-border)"
        },
        "checked": {
          "background": "var(--color-primary)",
          "border": "2px solid var(--color-primary)"
        },
        "indeterminate": {
          "background": "var(--color-primary)",
          "border": "2px solid var(--color-primary)"
        },
        "hover": {
          "borderColor": "var(--color-primary)",
          "boxShadow": "0 0 0 3px var(--color-primary-muted)"
        },
        "focus": {
          "boxShadow": "0 0 0 3px var(--color-primary-muted)"
        },
        "disabledUnchecked": {
          "background": "var(--color-disabled-surface)",
          "border": "2px solid var(--color-disabled-border)",
          "iconColor": "var(--color-disabled-icon)",
          "cursor": "not-allowed"
        },
        "disabledChecked": {
          "background": "var(--color-disabled-selected-surface)",
          "border": "2px solid var(--color-disabled-selected-border)",
          "iconColor": "var(--color-disabled-selected-text)",
          "cursor": "not-allowed"
        },
        "disabledIndeterminate": {
          "background": "var(--color-disabled-selected-surface)",
          "border": "2px solid var(--color-disabled-selected-border)",
          "iconColor": "var(--color-disabled-selected-text)",
          "cursor": "not-allowed"
        }
      }
    },
    "radio": {
      "size": "18px",
      "dotSize": "7px",
      "states": "same as checkbox (circular)",
      "iconFamily": "Material Symbols and Icons",
      "brand": {
        "unchecked": {
          "background": "color-mix(in oklch, var(--color-surface) 84%, transparent)",
          "border": "2px solid var(--color-border)"
        },
        "checked": {
          "background": "color-mix(in oklch, var(--color-surface) 90%, transparent)",
          "border": "2px solid var(--color-primary)",
          "dot": "var(--color-primary)"
        },
        "hover": {
          "borderColor": "var(--color-primary)",
          "boxShadow": "0 0 0 3px var(--color-primary-muted)"
        },
        "disabledUnchecked": {
          "background": "var(--color-disabled-surface)",
          "border": "2px solid var(--color-disabled-border)",
          "dot": "transparent",
          "cursor": "not-allowed"
        },
        "disabledChecked": {
          "background": "var(--color-disabled-surface)",
          "border": "2px solid var(--color-disabled-selected-border)",
          "dot": "var(--color-disabled-selected-border)",
          "cursor": "not-allowed"
        }
      }
    },
    "toggle": {
      "width": "40px",
      "height": "22px",
      "thumbSize": "16px",
      "states": {
        "off": {
          "background": "color-mix(in oklch, var(--color-border) 80%, transparent)"
        },
        "on": {
          "background": "var(--color-primary)"
        },
        "hover": {
          "boxShadow": "0 0 0 3px var(--color-primary-muted)"
        },
        "disabled": {
          "cursor": "not-allowed"
        }
      },
      "brand": {
        "off": {
          "background": "color-mix(in oklch, var(--color-border) 80%, transparent)"
        },
        "on": {
          "background": "var(--color-primary)"
        },
        "thumb": {
          "background": "var(--color-text-inverse)",
          "boxShadow": "0 1px 2px color-mix(in oklch, var(--color-text-primary) 18%, transparent)"
        },
        "hover": {
          "boxShadow": "0 0 0 3px var(--color-primary-muted)"
        },
        "disabledOff": {
          "background": "var(--color-disabled-surface)",
          "border": "1px solid var(--color-disabled-border)",
          "thumb": {
            "background": "var(--color-disabled-icon)",
            "boxShadow": "none"
          },
          "cursor": "not-allowed"
        },
        "disabledOn": {
          "background": "var(--color-disabled-selected-surface)",
          "border": "1px solid var(--color-disabled-selected-border)",
          "thumb": {
            "background": "var(--color-disabled-selected-text)",
            "boxShadow": "none"
          },
          "cursor": "not-allowed"
        }
      }
    },
    "card": {
      "variants": [
        "default",
        "outlined",
        "elevated",
        "luxury"
      ],
      "padding": "{spacing.5}",
      "borderRadius": "{borderRadius.lg}",
      "default": {
        "background": "var(--color-surface)",
        "boxShadow": "{shadow.modeAware.sm.value}"
      },
      "outlined": {
        "border": "1px solid var(--color-border)"
      },
      "elevated": {
        "boxShadow": "{shadow.modeAware.md.value}"
      },
      "luxury": {
        "border": "1px solid {color.primitive.kin.300.value}",
        "boxShadow": "{shadow.modeAware.gold.value}"
      },
      "states": {
        "hover": {
          "boxShadow": "{shadow.modeAware.md.value}",
          "transform": "translateY(-2px)"
        },
        "active": {
          "transform": "translateY(0)"
        }
      }
    },
    "badge": {
      "variants": [
        "default",
        "success",
        "warning",
        "error",
        "info",
        "luxury"
      ],
      "sizes": {
        "sm": {
          "paddingX": "{spacing.2}",
          "paddingY": "2px",
          "fontSize": "{typography.ui.caption.fontSize.value}"
        },
        "md": {
          "paddingX": "{spacing.2}",
          "paddingY": "{spacing.1}",
          "fontSize": "{typography.ui.bodySm.fontSize.value}"
        }
      },
      "borderRadius": "{borderRadius.full}"
    },
    "tag": {
      "closable": true,
      "sizes": {
        "sm": {
          "height": "22px",
          "fontSize": "{typography.ui.bodySm.fontSize.value}"
        },
        "md": {
          "height": "28px",
          "fontSize": "{typography.ui.bodyMd.fontSize.value}"
        }
      },
      "states": {
        "hover": {
          "background": "var(--color-surface-hover)"
        }
      }
    },
    "avatar": {
      "sizes": {
        "xs": {
          "size": "24px",
          "fontSize": "{typography.ui.caption.fontSize.value}"
        },
        "sm": {
          "size": "32px",
          "fontSize": "{typography.ui.bodySm.fontSize.value}"
        },
        "md": {
          "size": "40px",
          "fontSize": "{typography.ui.bodyMd.fontSize.value}"
        },
        "lg": {
          "size": "56px",
          "fontSize": "{typography.ui.bodyLg.fontSize.value}"
        },
        "xl": {
          "size": "80px",
          "fontSize": "{typography.ui.titleLg.fontSize.value}"
        }
      },
      "borderRadius": "{borderRadius.full}",
      "fallback": {
        "background": "var(--color-brand-muted)",
        "color": "var(--color-brand)"
      }
    },
    "tooltip": {
      "background": "var(--color-text-primary)",
      "color": "var(--color-text-inverse)",
      "fontSize": "{typography.ui.bodySm.fontSize.value}",
      "padding": "{spacing.2} {spacing.3}",
      "borderRadius": "{borderRadius.md}",
      "maxWidth": "240px",
      "arrowSize": "6px",
      "animation": {
        "duration": "{animation.duration.fast.value}",
        "easing": "{animation.easing.enter.value}"
      }
    },
    "modal": {
      "confirmDestructiveRequired": true,
      "closeIcon": "close",
      "iconFamily": "Material Symbols and Icons",
      "sizes": {
        "sm": {
          "maxWidth": "400px"
        },
        "md": {
          "maxWidth": "560px"
        },
        "lg": {
          "maxWidth": "720px"
        },
        "full": {
          "maxWidth": "calc(100vw - 64px)"
        }
      },
      "padding": "{spacing.6}",
      "borderRadius": "{borderRadius.xl}",
      "overlay": "var(--color-overlay)",
      "animation": {
        "enter": "scaleIn {animation.duration.normal.value} {animation.easing.enter.value}",
        "exit": "fadeOut {animation.duration.fast.value} {animation.easing.exit.value}"
      }
    },
    "drawer": {
      "sizes": {
        "sm": {
          "width": "320px"
        },
        "md": {
          "width": "480px"
        },
        "lg": {
          "width": "640px"
        }
      },
      "positions": [
        "left",
        "right",
        "top",
        "bottom"
      ],
      "overlay": "var(--color-overlay)"
    },
    "toast": {
      "variants": [
        "success",
        "error",
        "warning",
        "info"
      ],
      "width": "340px",
      "padding": "{spacing.3} {spacing.4}",
      "borderRadius": "{borderRadius.lg}",
      "boxShadow": "{shadow.modeAware.lg.value}",
      "animation": "slideRight {animation.duration.normal.value} {animation.easing.enter.value}",
      "autoDismiss": "5000ms"
    },
    "alert": {
      "variants": [
        "success",
        "error",
        "warning",
        "info"
      ],
      "padding": "{spacing.3} {spacing.4}",
      "borderRadius": "{borderRadius.md}",
      "borderLeft": "4px solid",
      "states": {
        "dismissible": true
      }
    },
    "tabs": {
      "variants": [
        "underline",
        "solid",
        "outline"
      ],
      "sizes": {
        "sm": {
          "height": "32px",
          "fontSize": "{typography.ui.bodySm.fontSize.value}"
        },
        "md": {
          "height": "40px",
          "fontSize": "{typography.ui.bodyMd.fontSize.value}"
        }
      },
      "indicator": {
        "underline": {
          "height": "2px",
          "color": "var(--color-brand)",
          "animation": "slide {animation.duration.normal.value}"
        },
        "solid": {
          "background": "var(--color-brand)",
          "borderRadius": "{borderRadius.md}"
        }
      },
      "states": {
        "default": {
          "color": "var(--color-text-secondary)"
        },
        "active": {
          "color": "var(--color-text-primary)"
        },
        "hover": {
          "color": "var(--color-text-primary)"
        },
        "disabled": {
          "color": "var(--color-disabled-text)",
          "opacity": "1",
          "cursor": "not-allowed"
        }
      }
    },
    "breadcrumb": {
      "separator": "／",
      "fontSize": "{typography.ui.bodySm.fontSize.value}",
      "activeColor": "var(--color-text-primary)",
      "inactiveColor": "var(--color-text-secondary)"
    },
    "pagination": {
      "itemSize": "36px",
      "borderRadius": "{borderRadius.md}",
      "active": {
        "background": "var(--color-brand)",
        "color": "var(--color-text-inverse)"
      },
      "states": {
        "hover": {
          "background": "var(--color-surface-hover)"
        }
      }
    },
    "navbar": {
      "height": "56px",
      "background": "color-mix(in oklch, var(--color-background) 85%, transparent)",
      "backdropFilter": "blur(12px) saturate(180%)",
      "borderBottom": "1px solid var(--color-border-subtle)",
      "zIndex": 1000
    },
    "sidebar": {
      "width": "272px",
      "collapsedWidth": "68px",
      "background": "var(--color-background-alt)",
      "borderRight": "1px solid var(--color-border-subtle)"
    },
    "footer": {
      "paddingY": "{spacing.12}",
      "background": "{color.primitive.sumi.800.value}",
      "color": "var(--color-text-inverse)"
    },
    "divider": {
      "variants": [
        "solid",
        "dashed",
        "dotted",
        "decorative"
      ],
      "color": "var(--color-border)",
      "thickness": "1px",
      "decorative": {
        "pattern": "wave",
        "description": "波 Nami — traditional wave pattern divider"
      }
    },
    "skeleton": {
      "background": "var(--color-background-alt)",
      "highlight": "var(--color-surface)",
      "borderRadius": "{borderRadius.md}",
      "animation": "shimmer 1.5s ease infinite"
    },
    "progressBar": {
      "height": "6px",
      "borderRadius": "{borderRadius.full}",
      "track": "var(--color-background-alt)",
      "fill": "var(--color-primary)",
      "luxuryFill": "linear-gradient(90deg, {color.primitive.kin.400.value}, {color.primitive.kin.600.value})"
    },
    "spinner": {
      "sizes": {
        "sm": "14px",
        "md": "20px",
        "lg": "32px"
      },
      "color": "var(--color-primary)",
      "trackColor": "var(--color-border)",
      "animation": "spin 0.8s linear infinite"
    },
    "accordion": {
      "borderBottom": "1px solid var(--color-border)",
      "paddingY": "{spacing.3}",
      "icon": "expand_more",
      "iconFamily": "Material Symbols and Icons",
      "animation": "{animation.duration.normal.value} {animation.easing.default.value}",
      "states": {
        "hover": {
          "background": "var(--color-surface-hover)"
        },
        "expanded": {
          "icon-rotation": "180deg"
        }
      }
    },
    "table": {
      "interactionDataAttributes": [
        "data-action",
        "data-col",
        "data-row",
        "data-row-menu",
        "data-resize-col"
      ],
      "headerBackground": "var(--color-background-alt)",
      "headerFontWeight": "{typography.fontWeight.semibold.value}",
      "cellPadding": "{spacing.2} {spacing.3}",
      "borderBottom": "1px solid var(--color-border-subtle)",
      "striped": {
        "oddRowBackground": "var(--color-background-alt)"
      },
      "hover": {
        "rowBackground": "var(--color-surface-hover)"
      },
      "sortable": {
        "indicator": "▲▼"
      }
    },
    "dropdown": {
      "minWidth": "200px",
      "maxHeight": "320px",
      "padding": "{spacing.1}",
      "borderRadius": "{borderRadius.lg}",
      "boxShadow": "{shadow.modeAware.lg.value}",
      "item": {
        "padding": "{spacing.2} {spacing.3}",
        "borderRadius": "{borderRadius.md}",
        "hover": {
          "background": "var(--color-surface-hover)"
        },
        "active": {
          "background": "var(--color-brand-muted)"
        }
      }
    },
    "stepper": {
      "dotSize": "28px",
      "lineHeight": "2px",
      "completed": {
        "background": "var(--color-brand)"
      },
      "current": {
        "border": "2px solid var(--color-brand)"
      },
      "upcoming": {
        "border": "2px solid var(--color-border)"
      }
    }
  },
  "accessibility": {
    "_description": "WCAG 2.1 AA compliance requirements",
    "contrast": {
      "normalText": {
        "value": "4.5:1"
      },
      "largeText": {
        "value": "3:1"
      },
      "uiComponents": {
        "value": "3:1"
      }
    },
    "focus": {
      "visible": {
        "value": true
      },
      "style": {
        "value": "2px solid var(--color-focus)"
      },
      "offset": {
        "value": "2px"
      }
    },
    "motion": {
      "prefersReducedMotion": {
        "value": true
      },
      "reducedAlternative": {
        "value": "opacity transitions only"
      }
    },
    "targets": {
      "minimumSize": {
        "value": "44px × 44px"
      },
      "minimumSpacing": {
        "value": "8px"
      }
    },
    "textResizing": {
      "support": {
        "value": "200%"
      }
    },
    "colorIndependence": {
      "value": true,
      "description": "Information not conveyed by color alone"
    },
    "darkModeGuidelines": {
      "_description": "Operational guidance for visually comfortable dark mode.",
      "avoidPureBlackAndWhite": true,
      "backgroundStrategy": "Use near-black surfaces with small lightness steps between layers.",
      "surfaceHierarchy": {
        "background": "#121212",
        "backgroundAlt": "#181818",
        "surface": "#1B1B1B",
        "elevated": "#1E1E1E",
        "hover": "#232323"
      },
      "textUsage": {
        "primary": "Use for all body copy and essential labels.",
        "secondary": "Use for metadata, helper text, and supporting information only.",
        "tertiary": "Use only for placeholders, disabled text, and low-priority chrome; never for body copy."
      },
      "textTargets": {
        "primary": "#EDEDED",
        "secondary": "#B3B3B3",
        "tertiary": "#8C8C8C"
      },
      "borderStrategy": {
        "preferSolidNeutralBordersInDarkMode": true,
        "avoidAlphaOnlyHairlines": true,
        "recommendedRange": "#333333 to #3A3A3A",
        "strongBorder": "#5A5A5A"
      }
    },
    "disabledStates": {
      "_description": "Disabled UI should remain legible and should not rely on opacity alone.",
      "useOpacityOnly": {
        "value": false
      },
      "preserveReadableText": {
        "value": true
      },
      "preserveVisibleBorders": {
        "value": true
      },
      "distinguishSelectedDisabled": {
        "value": true
      }
    }
  }
}
